FoldingAtHomeControl/__init__.py
FoldingAtHomeControl/const.py
FoldingAtHomeControl/exceptions.py
FoldingAtHomeControl/foldingathomecontrol.py
FoldingAtHomeControl/pyonparser.py
FoldingAtHomeControl/serialconnection.py
pyfoldingathomecontrol-3.0.1.dist-info/LICENSE
pyfoldingathomecontrol-3.0.1.dist-info/METADATA
pyfoldingathomecontrol-3.0.1.dist-info/WHEEL
pyfoldingathomecontrol-3.0.1.dist-info/RECORD
