Metadata-Version: 2.1
Name: pyfoldingathomecontrol
Version: 3.0.1
Summary: Python library to get stats from your Folding@Home Clients
Home-page: http://github.com/eifinger/PyFoldingAtHomeControl
License: MIT
Keywords: Folding@Home,asyncio
Author: Kevin Stillhammer
Author-email: kevin.stillhammer@gmail.com
Requires-Python: >=3.8,<4.0
Classifier: Intended Audience :: Developers
Classifier: License :: OSI Approved :: MIT License
Classifier: Operating System :: OS Independent
Classifier: Programming Language :: Python
Classifier: Programming Language :: Python :: 3
Classifier: Programming Language :: Python :: 3.8
Classifier: Programming Language :: Python :: 3.9
Classifier: Programming Language :: Python :: 3.10
Classifier: Programming Language :: Python :: 3.11
Classifier: Programming Language :: Python :: 3
Classifier: Topic :: Software Development :: Libraries :: Python Modules
Project-URL: Repository, http://github.com/eifinger/PyFoldingAtHomeControl
